packaging_version_git/__init__.py
packaging_version_git/collector.py
packaging_version_git/version.py
packaging_version_git-0.1.2.dist-info/LICENSE
packaging_version_git-0.1.2.dist-info/METADATA
packaging_version_git-0.1.2.dist-info/WHEEL
packaging_version_git-0.1.2.dist-info/top_level.txt
packaging_version_git-0.1.2.dist-info/RECORD
